main.py
auths3-0.1.0.dist-info/METADATA
auths3-0.1.0.dist-info/WHEEL
auths3-0.1.0.dist-info/top_level.txt
auths3-0.1.0.dist-info/RECORD
