Metadata-Version: 2.4
Name: auths3
Version: 0.1.0
Summary: Generate secured S3 urls
Requires-Python: >=3.13
